motion/__init__.py
motion/client.py
motion/models/__init__.py
motion/resources/__init__.py
motion/resources/base.py
motion/resources/comment.py
motion/resources/project.py
motion/resources/schedule.py
motion/resources/task.py
motion/resources/user.py
motion/resources/workspace.py
python_motion-0.2.1.dist-info/LICENSE
python_motion-0.2.1.dist-info/METADATA
python_motion-0.2.1.dist-info/WHEEL
python_motion-0.2.1.dist-info/RECORD
