Metadata-Version: 2.3
Name: python-motion
Version: 0.2.1
Summary: 
License: MIT
Author: Lemuel Boyce
Author-email: lemuel@vokality.com
Requires-Python: >=3.11,<4.0
Classifier: License :: OSI Approved :: MIT License
Classifier: Programming Language :: Python :: 3
Classifier: Programming Language :: Python :: 3.11
Classifier: Programming Language :: Python :: 3.12
Classifier: Programming Language :: Python :: 3.13
Requires-Dist: pydantic (>=2.9.2,<3.0.0)
Requires-Dist: requests (>=2.32.0,<3.0.0)
